starknet_simple_deploy/__init__.py
starknet_simple_deploy/contract_data_writer.py
starknet_simple_deploy/contract_interaction.py
starknet_simple_deploy/declare_contract.py
starknet_simple_deploy/deploy_contract.py
starknet_simple_deploy/deployer_config.py
starknet_simple_deploy/initialize_contract.py
starknet_simple_deploy/utils/__init__.py
starknet_simple_deploy/utils/get_abi.py
starknet_simple_deploy-0.1.4.dist-info/METADATA
starknet_simple_deploy-0.1.4.dist-info/WHEEL
starknet_simple_deploy-0.1.4.dist-info/top_level.txt
starknet_simple_deploy-0.1.4.dist-info/RECORD
