Metadata-Version: 2.1
Name: starknet-simple-deploy
Version: 0.1.4
Summary: Starknet Simple Deploy
Home-page: UNKNOWN
Author: Web3Technologies LLC
Author-email: zach@web3technologies.io
License: UNKNOWN
Project-URL: Source Code, https://github.com/web3technologies/starknet_simple_deploy
Project-URL: Issue Tracker, https://github.com/web3technologies/starknet_simple_deploy/issues
Platform: UNKNOWN
Requires-Dist: aiohttp ==3.9.3
Requires-Dist: aiosignal ==1.3.1
Requires-Dist: asgiref ==3.7.2
Requires-Dist: async-timeout ==4.0.3
Requires-Dist: attrs ==23.2.0
Requires-Dist: crypto-cpp-py ==1.4.4
Requires-Dist: ecdsa ==0.18.0
Requires-Dist: frozenlist ==1.4.1
Requires-Dist: idna ==3.6
Requires-Dist: lark ==1.1.9
Requires-Dist: marshmallow-dataclass ==8.6.0
Requires-Dist: marshmallow-oneofschema ==3.1.1
Requires-Dist: marshmallow ==3.20.2
Requires-Dist: mpmath ==1.3.0
Requires-Dist: multidict ==6.0.5
Requires-Dist: mypy-extensions ==1.0.0
Requires-Dist: packaging ==23.2
Requires-Dist: poseidon-py ==0.1.4
Requires-Dist: pycryptodome ==3.20.0
Requires-Dist: python-decouple ==3.8
Requires-Dist: six ==1.16.0
Requires-Dist: starknet-py ==0.19.0
Requires-Dist: sympy ==1.11.1
Requires-Dist: toml ==0.10.2
Requires-Dist: typing-inspect ==0.9.0
Requires-Dist: typing-extensions ==4.9.0
Requires-Dist: yarl ==1.9.4
Provides-Extra: test
